[
  {
    "content_id": 658520,
    "reference_id": 203443,
    "title": "Acabe",
    "media_type": "Text",
    "index_reference": "acabe",
    "language": "por",
    "content": "<p>Acabe, o oitavo rei de Israel, assumiu o reino do norte de seu forte pai, Onri (<a href=\"https://ref.ly/1Kgs16:27-1Kgs16:28\">1Rs 16.27–28</a>). Ele governou Israel de 874 a 853 a.C. Acabe casou-se com Jezabel, a filha do Rei Etbaal de Sidom. Influenciado por ela, Acabe começou a adorar Baal em vez do Senhor (<a href=\"https://ref.ly/1Kgs16:29-1Kgs16:33\">1Rs 16.29–33</a>).</p><p>Acabe venceu várias batalhas. Ele derrotou os arameus (<a href=\"https://ref.ly/1Kgs20:1-1Kgs20:34\">1Rs 20.1–34</a>). Em 853 a.C., ele liderou um grupo de reis contra o rei assírio Salmaneser III, vencendo a Batalha de Qarqar. No entanto, o Antigo Testamento compartilha poucas boas-novas sobre Acabe, que traiu Deus. Deus enviou o profeta Elias para desafiar Acabe, Jezabel e seus profetas e para reafirmar a supremacia do verdadeiro Deus (<a href=\"https://ref.ly/1Kgs17:1\">1Rs 17.1</a>; <a href=\"https://ref.ly/1Kgs18:1-1Kgs18:46\">18.1–46</a>).</p><p>Acabe não apenas traiu o Senhor, mas também tratou mal seu povo, como mostrado na história de Nabote e sua vinha (<a href=\"https://ref.ly/1Kgs21:1-1Kgs21:29\">1Rs 21.1–29</a>). Em Israel, as pessoas possuíam suas terras como um presente de Deus. Quando Acabe quis tomar a vinha de Nabote e Nabote recusou, Acabe ficou frustrado. Jezabel, que conhecia um tipo diferente de realeza onde os reis tomavam o que queriam, ajudou Acabe contando mentiras sobre Nabote para que ele fosse morto. Nabote foi executado com acusações falsas, e Acabe tomou a terra. No entanto, o Senhor não deixou Acabe escapar do castigo. Ele enviou Elias para anunciar uma sentença de morte para Acabe e sua família.</p><p>A guerra recomeçou com Aram, e Acabe pediu a Josafá, o rei do sul, para ser seu aliado (<a href=\"https://ref.ly/1Kgs22:2-1Kgs22:4\">1Rs 22.2–4</a>; <a href=\"https://ref.ly/2Chr18:1-2Chr18:3\">2Cr 18.1–3</a>). Josafá ainda acreditava no Senhor, então ele convenceu Acabe a consultar o profeta de Deus, Micaías. Micaías previu que essa batalha terminaria com a morte de Acabe (<a href=\"https://ref.ly/1Kgs22:5-1Kgs22:28\">1Rs 22.5–28</a>; <a href=\"https://ref.ly/2Chr18:4-2Chr18:27\">2Cr 18.4–27</a>). Acabe tentou evitar isso usando uma armadura comum e fazendo Josafá vestir roupas de batalha reais como isca, mas ele não conseguiu enganar Deus. A flecha de um arqueiro atingiu a junta da armadura de Acabe, e ele morreu, &quot;conforme a palavra que o Senhor havia falado&quot; (<a href=\"https://ref.ly/1Kgs22:38\">1Rs 22.38</a>).</p><p><u>Passagens para estudo complementar</u></p><p><a href=\"https://ref.ly/1Kgs16:29-1Kgs22:53\">1 Reis 16.29–22.53</a>; <a href=\"https://ref.ly/2Chr18:1-2Chr18:34\">2 Crônicas 18.1–34</a>; <a href=\"https://ref.ly/Mic6:16\">Miquéias 6.16</a></p>",
    "associations": {
      "passage": [
        {
          "start_ref": "11017001",
          "start_ref_usfm": "1KI 17:1",
          "end_ref": "11017001",
          "end_ref_usfm": "1KI 17:1"
        },
        {
          "start_ref": "11022038",
          "start_ref_usfm": "1KI 22:38",
          "end_ref": "11022038",
          "end_ref_usfm": "1KI 22:38"
        },
        {
          "start_ref": "33006016",
          "start_ref_usfm": "MIC 6:16",
          "end_ref": "33006016",
          "end_ref_usfm": "MIC 6:16"
        },
        {
          "start_ref": "11022002",
          "start_ref_usfm": "1KI 22:2",
          "end_ref": "11022004",
          "end_ref_usfm": "1KI 22:4"
        },
        {
          "start_ref": "14018001",
          "start_ref_usfm": "2CH 18:1",
          "end_ref": "14018003",
          "end_ref_usfm": "2CH 18:3"
        },
        {
          "start_ref": "11022005",
          "start_ref_usfm": "1KI 22:5",
          "end_ref": "11022028",
          "end_ref_usfm": "1KI 22:28"
        },
        {
          "start_ref": "14018004",
          "start_ref_usfm": "2CH 18:4",
          "end_ref": "14018027",
          "end_ref_usfm": "2CH 18:27"
        },
        {
          "start_ref": "11021001",
          "start_ref_usfm": "1KI 21:1",
          "end_ref": "11021029",
          "end_ref_usfm": "1KI 21:29"
        },
        {
          "start_ref": "11016029",
          "start_ref_usfm": "1KI 16:29",
          "end_ref": "11016033",
          "end_ref_usfm": "1KI 16:33"
        },
        {
          "start_ref": "11018001",
          "start_ref_usfm": "1KI 18:1",
          "end_ref": "11018046",
          "end_ref_usfm": "1KI 18:46"
        },
        {
          "start_ref": "14018001",
          "start_ref_usfm": "2CH 18:1",
          "end_ref": "14018034",
          "end_ref_usfm": "2CH 18:34"
        },
        {
          "start_ref": "11020001",
          "start_ref_usfm": "1KI 20:1",
          "end_ref": "11020034",
          "end_ref_usfm": "1KI 20:34"
        },
        {
          "start_ref": "11016027",
          "start_ref_usfm": "1KI 16:27",
          "end_ref": "11016028",
          "end_ref_usfm": "1KI 16:28"
        },
        {
          "start_ref": "11016029",
          "start_ref_usfm": "1KI 16:29",
          "end_ref": "11022053",
          "end_ref_usfm": "1KI 22:53"
        }
      ],
      "resource": []
    }
  }
]