[
  {
    "content_id": 668851,
    "reference_id": 203393,
    "title": "Adam et Ève",
    "media_type": "Text",
    "index_reference": "adam et ève",
    "language": "fra",
    "content": "<p>Adam fut le premier homme et le père de l&apos;humanité. Dieu créa le premier couple à son image afin de remplir la terre et de gouverner la création (<a href=\"https://ref.ly/Gen1:26-Gen1:31\">Gn 1.26–31</a>). Dieu forma Adam à partir de la poussière de la terre et lui donna la vie&nbsp;(<a href=\"https://ref.ly/Gen2:7\">Gn 2.7</a>). Sa mission comprenait notamment :</p><ul><li><p>Entretenir le jardin dans lequel Dieu l’avait placé (<a href=\"https://ref.ly/Gen2:15\">Gn 2.15</a>)</p></li><li><p>Nommer les animaux (<a href=\"https://ref.ly/Gen2:19-Gen2:20\">Gn 2.19–20</a>)</p></li><li><p>Obéir aux instructions divines (<a href=\"https://ref.ly/Gen1:28\">Gn 1.28</a> ; <a href=\"https://ref.ly/Gen2:16-Gen2:17\">2.16–17</a>)</p></li></ul><p>Dieu créa la première femme, Ève, pour être la compagne et l&apos;aide d&apos;Adam. Il la créa à partir de la côte d’Adam (<a href=\"https://ref.ly/Gen2:18-Gen2:22\">Gn 2.18–22</a>), ce qui symbolise l&apos;unité que Dieu voulait pour le mariage (<a href=\"https://ref.ly/Gen2:23-Gen2:25\">Gn 2.23–25</a>). Elle est honorée comme « la mère de tous les vivants » (<a href=\"https://ref.ly/Gen3:20\">Gn 3.20</a>).</p><p>Cependant, l’harmonie fut rompue lorsque le serpent trompa Ève, l’incitant à désobéir à Dieu&nbsp; (<a href=\"https://ref.ly/Gen3:1-Gen3:6\">Gn 3.1–6</a>). Adam, à son tour, suivit son exemple, et leur rébellion endommagea leur relation (<a href=\"https://ref.ly/Gen3:7\">Gn 3.7</a>) tout en les séparant du Créateur. Dieu a cherché Adam après cette rébellion, mais Ève et lui se cachaient déjà parmi les arbres, ressentant déjà la séparation (<a href=\"https://ref.ly/Gen3:8\">Gn 3.8</a>). </p><p>Lorsque interrogé, Adam rejeta la responsabilité sur Ève et, indirectement, sur Dieu (<a href=\"https://ref.ly/Gen3:12\">Gn 3.12</a>). Cette désobéissance engendra douleur, tensions relationnelles, difficultés matérielles (ex : cultiver la terre) ainsi que la mort physique et spirituelle (<a href=\"https://ref.ly/Gen3:16-Gen3:19\">Gn 3.16–19</a>, <a href=\"https://ref.ly/Gen3:22-Gen3:24\">22–24</a>). Néanmoins, Dieu fournit des peaux d’animaux pour vêtir Adam et Ève (<a href=\"https://ref.ly/Gen3:21\">Gn 3.21</a>), et promit que les descendants d’Ève triompheraient de Satan (<a href=\"https://ref.ly/Gen3:15\">Gn 3.15</a> ; voir <a href=\"https://ref.ly/Rom16:20\">Rm 16.20</a> ; <a href=\"https://ref.ly/Rev12:1-Rev12:9\">Ap 12.1–9</a> ; <a href=\"https://ref.ly/Rev20:1-Rev20:10\">20.1–10</a>).</p><p>Adam était une personne historique (<a href=\"https://ref.ly/Gen4:25\">Gn 4.25</a> ; <a href=\"https://ref.ly/Gen5:1-Gen5:5\">5.1–5</a> ; <a href=\"https://ref.ly/1Chr1:1\">1Ch 1.1</a> ; <a href=\"https://ref.ly/Hos6:7\">Os 6.7</a> ; <a href=\"https://ref.ly/Luke3:38\">Lc 3.38</a> ; <a href=\"https://ref.ly/Rom5:14\">Rm 5.14</a> ; <a href=\"https://ref.ly/1Cor15:22\">1Co 15.22</a>, <a href=\"https://ref.ly/1Cor15:45\">45</a> ; <a href=\"https://ref.ly/1Tim2:13-1Tim2:14\">1Tm 2.13–14</a> ; <a href=\"https://ref.ly/Jude1:14\">Jd 1.14</a>) qui est aussi le symbole de l’humanité tout entière. Les commandements donnés par Dieu dans <a href=\"https://ref.ly/Gen1:26-Gen1:30\">Gn 1.26–30</a> et les malédictions prononcées dans <a href=\"https://ref.ly/Gen3:16-Gen3:19\">3.16–19</a> ont eu des répercussions non seulement sur Adam et Ève, mais sur toute l’espèce humaine, témoignage de la séparation originelle d’avec Dieu.</p><p>L’apôtre Paul a établi un parallèle saisissant entre Adam, le premier homme, et Jésus-Christ, qualifié de « dernier Adam »&nbsp; (<a href=\"https://ref.ly/Rom5:12-Rom5:21\">Rm 5.12–21</a> ; <a href=\"https://ref.ly/1Cor15:45-1Cor15:50\">1Co 15.45–50</a> ; voir aussi <a href=\"https://ref.ly/Rom8:5-Rom8:11\">Rm 8.5–11</a>, <a href=\"https://ref.ly/Rom8:20-Rom8:22\">20–22</a>). Les personnes représentées par Adam vivent comme lui, goutant au péché, à la séparation d&apos;avec Dieu et la création, ainsi qu&apos;à la mort spirituelle. En revanche, ceux qui suivent Jésus vivent par la foi en lui. Ils sont, en un sens, recréés à l’image du Christ et deviennent de « nouvelles personnes », participant à une création renouvelée (voir <a href=\"https://ref.ly/Rom8:29\">Rm 8.29</a> ; <a href=\"https://ref.ly/1Cor15:49\">1Co 15.49</a> ; <a href=\"https://ref.ly/2Cor5:17\">2Co 5.17</a> ; <a href=\"https://ref.ly/Gal6:15\">Ga 6.15</a>). Jésus enlève les barrières instaurées par Adam et Ève (<a href=\"https://ref.ly/Rom5:1\">Rm 5.1</a> ; <a href=\"https://ref.ly/2Cor5:19\">2Co 5.19</a> ; <a href=\"https://ref.ly/Gal3:27-Gal3:28\">Ga 3.27–28</a> ; <a href=\"https://ref.ly/Eph2:14-Eph2:16\">Ep 2.14–16</a>), restaurant ainsi ce qui avait été perdu.</p><p><u>Passages pour une étude approfondie</u></p><p><a href=\"https://ref.ly/Gen1:26-Gen1:31\">Genèse 1.26–31</a> ; <a href=\"https://ref.ly/Gen2:4-Gen3:24\">2.4–3.24</a> ; <a href=\"https://ref.ly/Gen4:25-Gen5:5\">4.25–5.5</a> ; <a href=\"https://ref.ly/Hos6:6-Hos6:7\">Osée 6.6–7</a> ; <a href=\"https://ref.ly/Luke3:38\">Luc 3.38</a> ; <a href=\"https://ref.ly/Rom5:12-Rom5:21\">Romains 5.12–21</a> ; <a href=\"https://ref.ly/1Cor15:22\">1 Corinthiens 15.22</a>, <a href=\"https://ref.ly/1Cor15:45-1Cor15:49\">45–49</a> ; <a href=\"https://ref.ly/1Tim2:13-1Tim2:14\">1 Timothée 2.13–14</a></p>",
    "associations": {
      "passage": [
        {
          "start_ref": "01001028",
          "start_ref_usfm": "GEN 1:28",
          "end_ref": "01001028",
          "end_ref_usfm": "GEN 1:28"
        },
        {
          "start_ref": "01002007",
          "start_ref_usfm": "GEN 2:7",
          "end_ref": "01002007",
          "end_ref_usfm": "GEN 2:7"
        },
        {
          "start_ref": "01002015",
          "start_ref_usfm": "GEN 2:15",
          "end_ref": "01002015",
          "end_ref_usfm": "GEN 2:15"
        },
        {
          "start_ref": "01003007",
          "start_ref_usfm": "GEN 3:7",
          "end_ref": "01003007",
          "end_ref_usfm": "GEN 3:7"
        },
        {
          "start_ref": "01003008",
          "start_ref_usfm": "GEN 3:8",
          "end_ref": "01003008",
          "end_ref_usfm": "GEN 3:8"
        },
        {
          "start_ref": "01003012",
          "start_ref_usfm": "GEN 3:12",
          "end_ref": "01003012",
          "end_ref_usfm": "GEN 3:12"
        },
        {
          "start_ref": "01003015",
          "start_ref_usfm": "GEN 3:15",
          "end_ref": "01003015",
          "end_ref_usfm": "GEN 3:15"
        },
        {
          "start_ref": "01003020",
          "start_ref_usfm": "GEN 3:20",
          "end_ref": "01003020",
          "end_ref_usfm": "GEN 3:20"
        },
        {
          "start_ref": "01003021",
          "start_ref_usfm": "GEN 3:21",
          "end_ref": "01003021",
          "end_ref_usfm": "GEN 3:21"
        },
        {
          "start_ref": "01004025",
          "start_ref_usfm": "GEN 4:25",
          "end_ref": "01004025",
          "end_ref_usfm": "GEN 4:25"
        },
        {
          "start_ref": "13001001",
          "start_ref_usfm": "1CH 1:1",
          "end_ref": "13001001",
          "end_ref_usfm": "1CH 1:1"
        },
        {
          "start_ref": "28006007",
          "start_ref_usfm": "HOS 6:7",
          "end_ref": "28006007",
          "end_ref_usfm": "HOS 6:7"
        },
        {
          "start_ref": "42003038",
          "start_ref_usfm": "LUK 3:38",
          "end_ref": "42003038",
          "end_ref_usfm": "LUK 3:38"
        },
        {
          "start_ref": "45005001",
          "start_ref_usfm": "ROM 5:1",
          "end_ref": "45005001",
          "end_ref_usfm": "ROM 5:1"
        },
        {
          "start_ref": "45005014",
          "start_ref_usfm": "ROM 5:14",
          "end_ref": "45005014",
          "end_ref_usfm": "ROM 5:14"
        },
        {
          "start_ref": "45008029",
          "start_ref_usfm": "ROM 8:29",
          "end_ref": "45008029",
          "end_ref_usfm": "ROM 8:29"
        },
        {
          "start_ref": "45016020",
          "start_ref_usfm": "ROM 16:20",
          "end_ref": "45016020",
          "end_ref_usfm": "ROM 16:20"
        },
        {
          "start_ref": "46015022",
          "start_ref_usfm": "1CO 15:22",
          "end_ref": "46015022",
          "end_ref_usfm": "1CO 15:22"
        },
        {
          "start_ref": "46015045",
          "start_ref_usfm": "1CO 15:45",
          "end_ref": "46015045",
          "end_ref_usfm": "1CO 15:45"
        },
        {
          "start_ref": "46015049",
          "start_ref_usfm": "1CO 15:49",
          "end_ref": "46015049",
          "end_ref_usfm": "1CO 15:49"
        },
        {
          "start_ref": "47005017",
          "start_ref_usfm": "2CO 5:17",
          "end_ref": "47005017",
          "end_ref_usfm": "2CO 5:17"
        },
        {
          "start_ref": "47005019",
          "start_ref_usfm": "2CO 5:19",
          "end_ref": "47005019",
          "end_ref_usfm": "2CO 5:19"
        },
        {
          "start_ref": "48006015",
          "start_ref_usfm": "GAL 6:15",
          "end_ref": "48006015",
          "end_ref_usfm": "GAL 6:15"
        },
        {
          "start_ref": "65001014",
          "start_ref_usfm": "JUD 1:14",
          "end_ref": "65001014",
          "end_ref_usfm": "JUD 1:14"
        },
        {
          "start_ref": "01001026",
          "start_ref_usfm": "GEN 1:26",
          "end_ref": "01001031",
          "end_ref_usfm": "GEN 1:31"
        },
        {
          "start_ref": "01002004",
          "start_ref_usfm": "GEN 2:4",
          "end_ref": "01003024",
          "end_ref_usfm": "GEN 3:24"
        },
        {
          "start_ref": "01002016",
          "start_ref_usfm": "GEN 2:16",
          "end_ref": "01002017",
          "end_ref_usfm": "GEN 2:17"
        },
        {
          "start_ref": "01002018",
          "start_ref_usfm": "GEN 2:18",
          "end_ref": "01002022",
          "end_ref_usfm": "GEN 2:22"
        },
        {
          "start_ref": "01005001",
          "start_ref_usfm": "GEN 5:1",
          "end_ref": "01005005",
          "end_ref_usfm": "GEN 5:5"
        },
        {
          "start_ref": "54002013",
          "start_ref_usfm": "1TI 2:13",
          "end_ref": "54002014",
          "end_ref_usfm": "1TI 2:14"
        },
        {
          "start_ref": "01001026",
          "start_ref_usfm": "GEN 1:26",
          "end_ref": "01001030",
          "end_ref_usfm": "GEN 1:30"
        },
        {
          "start_ref": "01003016",
          "start_ref_usfm": "GEN 3:16",
          "end_ref": "01003019",
          "end_ref_usfm": "GEN 3:19"
        },
        {
          "start_ref": "45005012",
          "start_ref_usfm": "ROM 5:12",
          "end_ref": "45005021",
          "end_ref_usfm": "ROM 5:21"
        },
        {
          "start_ref": "46015045",
          "start_ref_usfm": "1CO 15:45",
          "end_ref": "46015050",
          "end_ref_usfm": "1CO 15:50"
        },
        {
          "start_ref": "45008020",
          "start_ref_usfm": "ROM 8:20",
          "end_ref": "45008022",
          "end_ref_usfm": "ROM 8:22"
        },
        {
          "start_ref": "48003027",
          "start_ref_usfm": "GAL 3:27",
          "end_ref": "48003028",
          "end_ref_usfm": "GAL 3:28"
        },
        {
          "start_ref": "49002014",
          "start_ref_usfm": "EPH 2:14",
          "end_ref": "49002016",
          "end_ref_usfm": "EPH 2:16"
        },
        {
          "start_ref": "46015045",
          "start_ref_usfm": "1CO 15:45",
          "end_ref": "46015049",
          "end_ref_usfm": "1CO 15:49"
        },
        {
          "start_ref": "01002019",
          "start_ref_usfm": "GEN 2:19",
          "end_ref": "01002020",
          "end_ref_usfm": "GEN 2:20"
        },
        {
          "start_ref": "01003022",
          "start_ref_usfm": "GEN 3:22",
          "end_ref": "01003024",
          "end_ref_usfm": "GEN 3:24"
        },
        {
          "start_ref": "66020001",
          "start_ref_usfm": "REV 20:1",
          "end_ref": "66020010",
          "end_ref_usfm": "REV 20:10"
        },
        {
          "start_ref": "01003001",
          "start_ref_usfm": "GEN 3:1",
          "end_ref": "01003006",
          "end_ref_usfm": "GEN 3:6"
        },
        {
          "start_ref": "01002023",
          "start_ref_usfm": "GEN 2:23",
          "end_ref": "01002025",
          "end_ref_usfm": "GEN 2:25"
        },
        {
          "start_ref": "66012001",
          "start_ref_usfm": "REV 12:1",
          "end_ref": "66012009",
          "end_ref_usfm": "REV 12:9"
        },
        {
          "start_ref": "45008005",
          "start_ref_usfm": "ROM 8:5",
          "end_ref": "45008011",
          "end_ref_usfm": "ROM 8:11"
        },
        {
          "start_ref": "01004025",
          "start_ref_usfm": "GEN 4:25",
          "end_ref": "01005005",
          "end_ref_usfm": "GEN 5:5"
        },
        {
          "start_ref": "28006006",
          "start_ref_usfm": "HOS 6:6",
          "end_ref": "28006007",
          "end_ref_usfm": "HOS 6:7"
        }
      ],
      "resource": []
    }
  }
]